git_history_analyzer.py
git_history_analyzer-0.0.13.dist-info/LICENSE
git_history_analyzer-0.0.13.dist-info/METADATA
git_history_analyzer-0.0.13.dist-info/WHEEL
git_history_analyzer-0.0.13.dist-info/top_level.txt
git_history_analyzer-0.0.13.dist-info/RECORD
