Metadata-Version: 2.1
Name: git-history-analyzer
Version: 0.0.13
Summary: Generate Reports from Your Repository's Git History
Home-page: https://github.com/jorgecardona/git-history-analyzer
Author: Jorge Cardona
Classifier: Programming Language :: Python :: 3
Classifier: License :: OSI Approved :: MIT License
Classifier: Operating System :: OS Independent
Requires-Python: >=3.6
License-File: LICENSE
